{
  "life-orb": "생명의구슬",
  "expert-belt": "달인의띠",
  "metronome": "메트로놈",
  "silk-scarf": "실크스카프",
  "charcoal": "목탄",
  "mystic-water": "신비의물방울",
  "miracle-seed": "기적의씨",
  "magnet": "자석",
  "never-melt-ice": "녹지않는얼음",
  "black-belt": "검은띠",
  "poison-barb": "독바늘",
  "soft-sand": "부드러운모래",
  "sharp-beak": "예리한부리",
  "twisted-spoon": "휘어진스푼",
  "silver-powder": "은빛가루",
  "hard-stone": "딱딱한돌",
  "spell-tag": "저주의부적",
  "dragon-fang": "용의이빨",
  "black-glasses": "검은안경",
  "metal-coat": "금속코트",
  "fairy-feather": "요정의깃털",
  "normal-gem": "노말주얼",
  "fire-gem": "불꽃주얼",
  "water-gem": "물주얼",
  "electric-gem": "전기주얼",
  "grass-gem": "풀주얼",
  "ice-gem": "얼음주얼",
  "fighting-gem": "격투주얼",
  "poison-gem": "독주얼",
  "ground-gem": "땅주얼",
  "flying-gem": "비행주얼",
  "psychic-gem": "에스퍼주얼",
  "bug-gem": "벌레주얼",
  "rock-gem": "바위주얼",
  "ghost-gem": "고스트주얼",
  "dragon-gem": "드래곤주얼",
  "dark-gem": "악주얼",
  "steel-gem": "강철주얼",
  "fairy-gem": "페어리주얼",
  "flame-plate": "불구슬플레이트",
  "splash-plate": "물방울플레이트",
  "zap-plate": "우뢰플레이트",
  "meadow-plate": "초록플레이트",
  "icicle-plate": "고드름플레이트",
  "fist-plate": "주먹플레이트",
  "toxic-plate": "맹독플레이트",
  "earth-plate": "대지플레이트",
  "sky-plate": "푸른하늘플레이트",
  "mind-plate": "이상한플레이트",
  "insect-plate": "비단벌레플레이트",
  "stone-plate": "암석플레이트",
  "spooky-plate": "원령플레이트",
  "draco-plate": "용의플레이트",
  "dread-plate": "공포플레이트",
  "iron-plate": "강철플레이트",
  "pixie-plate": "정령플레이트",
  "scope-lens": "초점렌즈",
  "razor-claw": "예리한손톱",
  "wide-lens": "광각렌즈",
  "zoom-lens": "포커스렌즈",
  "choice-band": "구애머리띠",
  "choice-specs": "구애안경",
  "choice-scarf": "구애스카프",
  "muscle-band": "힘의머리띠",
  "wise-glasses": "박식안경",
  "eviolite": "진화의휘석",
  "assault-vest": "돌격조끼",
  "punching-glove": "펀치글러브",
  "berserk-gene": "파괴의 유전자",
  "cell-battery": "충전지",
  "absorb-bulb": "구근",
  "luminous-moss": "빛이끼",
  "snowball": "눈덩이",
  "weakness-policy": "약점보험",
  "blunder-policy": "허탕보험",
  "electric-seed": "일렉트릭시드",
  "grassy-seed": "그래스시드",
  "psychic-seed": "사이코시드",
  "misty-seed": "미스트시드",
  "adrenaline-orb": "주눅구슬",
  "room-service": "룸서비스",
  "throat-spray": "목스프레이",
  "mirror-herb": "흉내허브",
  "light-ball": "전기구슬",
  "thick-club": "굵은뼈",
  "leek": "대파",
  "lucky-punch": "럭키펀치",
  "metal-powder": "금속파우더",
  "quick-powder": "스피드파우더",
  "deep-sea-tooth": "심해의이빨",
  "deep-sea-scale": "심해의비늘",
  "blue-orb": "쪽빛구슬",
  "red-orb": "주홍구슬",
  "soul-dew": "마음의물방울",
  "adamant-orb": "금강옥",
  "adamant-crystal": "큰금강옥",
  "lustrous-orb": "백옥",
  "lustrous-globe": "큰백옥",
  "griseous-orb": "백금옥",
  "griseous-core": "큰백금옥",
  "burn-drive": "불꽃카세트",
  "douse-drive": "물카세트",
  "chill-drive": "얼음카세트",
  "shock-drive": "전기카세트",
  "fighting-memory": "파이팅메모리",
  "flying-memory": "플라잉메모리",
  "poison-memory": "포이즌메모리",
  "ground-memory": "그라운드메모리",
  "rock-memory": "락메모리",
  "bug-memory": "버그메모리",
  "ghost-memory": "고스트메모리",
  "steel-memory": "스틸메모리",
  "fire-memory": "파이어메모리",
  "water-memory": "워터메모리",
  "grass-memory": "그라스메모리",
  "electric-memory": "일렉트릭메모리",
  "psychic-memory": "사이키메모리",
  "ice-memory": "아이스메모리",
  "dragon-memory": "드래곤메모리",
  "dark-memory": "다크메모리",
  "fairy-memory": "페어리메모리",
  "rusted-sword": "녹슨검",
  "rusted-shield": "녹슨방패",
  "booster-energy": "부스트에너지",
  "hearthflame-mask": "화덕의가면",
  "wellspring-mask": "우물의가면",
  "cornerstone-mask": "주춧돌의가면",
  "leftovers": "먹다남은음식",
  "shell-bell": "조개껍질방울",
  "black-sludge": "검은오물",
  "big-root": "큰뿌리",
  "focus-sash": "기합의띠",
  "focus-band": "기합의머리띠",
  "white-herb": "하양허브",
  "mental-herb": "멘탈허브",
  "air-balloon": "풍선",
  "safety-goggles": "방진고글",
  "protective-pads": "방호패드",
  "heavy-duty-boots": "통굽부츠",
  "utility-umbrella": "만능우산",
  "clear-amulet": "클리어참",
  "covert-cloak": "은밀망토",
  "ability-shield": "특성가드",
  "shed-shell": "아름다운허물",
  "red-card": "레드카드",
  "eject-button": "탈출버튼",
  "eject-pack": "탈출팩",
  "grip-claw": "끈기갈고리손톱",
  "light-clay": "빛의점토",
  "icy-rock": "차가운바위",
  "smooth-rock": "보송보송바위",
  "heat-rock": "뜨거운바위",
  "damp-rock": "축축한바위",
  "terrain-extender": "그라운드코트",
  "flame-orb": "화염구슬",
  "toxic-orb": "맹독구슬",
  "sticky-barb": "끈적끈적바늘",
  "ring-target": "겨냥표적",
  "destiny-knot": "빨간실",
  "quick-claw": "선제공격손톱",
  "bright-powder": "반짝가루",
  "kings-rock": "왕의징표석",
  "razor-fang": "예리한이빨",
  "lagging-tail": "느림보꼬리",
  "float-stone": "가벼운돌",
  "rocky-helmet": "울퉁불퉁멧",
  "iron-ball": "검은철구",
  "binding-band": "조임밴드",
  "power-herb": "파워풀허브",
  "loaded-dice": "속임수주사위",
  "sitrus-berry": "자뭉열매",
  "starf-berry": "스타열매"
}
